ALU.v
module Alu #(
    parameter bus_width = 8
)(
    input  [bus_width-1:0] A,
    input  [bus_width-1:0] B,
    input  [3:0] opcode,
    input  car_in,
    output reg [bus_width-1:0] y,
    output reg Car_out,
    output reg borrow,
    output zero,
    output parity,
    output reg invalid_op
);

    // Opcode definitions
    localparam op_add             = 4'd1;
    localparam op_add_with_carry = 4'd2;
    localparam op_sub            = 4'd3;
    localparam op_inc            = 4'd4;
    localparam op_dec            = 4'd5;
    localparam op_and            = 4'd6;
    localparam op_not            = 4'd7;
    localparam op_rol            = 4'd8;
    localparam op_ror            = 4'd9;

    always @(*) begin
    
        y = 0;
        Car_out = 0;
        borrow = 0;
        invalid_op = 0;

        case (opcode)
            // ADD
            op_add: begin
                {Car_out, y} = A + B; 
            end

            // ADD with carry
            op_add_with_carry: begin
                {Car_out, y} = A + B + (car_in & 1'b1); 
            end

            // SUBTRACT
            op_sub: begin
                y = A - B;
                borrow = (A < B);
            end

            // INCREMENT
            op_inc: begin
                {Car_out, y} = A + 1;
            end

            // DECREMENT
            op_dec: begin
                y = A - 1;
                borrow = (A == 0);
            end

            // AND
            op_and: begin
                y = A & B;
            end

            // NOT
            op_not: begin
                y = ~A;
            end

            // ROTATE LEFT
            op_rol: begin
                y = {A[bus_width-2:0], A[bus_width-1]};
            end

            // ROTATE RIGHT
            op_ror: begin
                y = {A[0], A[bus_width-1:1]};
            end


            default: begin
                invalid_op = 1;
            end
        endcase
    end

    assign zero   = (y == 0);
    assign parity = ^y; 

endmodule

tb_ALU.v
module alu_tb;
    reg  [7:0] A, B;
    reg  [3:0] opcode;
    reg        car_in;
    wire [7:0] y;
    wire       Car_out, borrow, zero, parity;
    wire       invalid_op;

    Alu uut (
        .A(A), .B(B),
        .opcode(opcode),
        .car_in(car_in),
        .y(y),
        .Car_out(Car_out),
        .borrow(borrow),
        .zero(zero),
        .parity(parity),
        .invalid_op(invalid_op)
    );

    initial begin
        $dumpfile("alu_tb.vcd");
        $dumpvars(0, alu_tb);

        A = 8'd10; B = 8'd5; car_in = 0; opcode = 4'd1; #10;
        $display("ADD     : A=%d B=%d Y=%d Car_out=%b", A, B, y, Car_out);

        A = 8'd200; B = 8'd100; car_in = 1; opcode = 4'd2; #10;
        $display("ADC     : A=%d B=%d Y=%d Car_out=%b", A, B, y, Car_out);

        A = 8'd5; B = 8'd10; car_in = 0; opcode = 4'd3; #10;
        $display("SUB     : A=%d B=%d Y=%d Borrow=%b", A, B, y, borrow);

        A = 8'd255; B = 8'd0; car_in = 0; opcode = 4'd4; #10;
        $display("INC     : A=%d Y=%d Car_out=%b", A, y, Car_out);

        A = 8'd0; B = 8'd0; car_in = 0; opcode = 4'd5; #10;
        $display("DEC     : A=%d Y=%d Borrow=%b", A, y, borrow);

        A = 8'd170; B = 8'd85; car_in = 0; opcode = 4'd6; #10;
        $display("AND     : A=%b B=%b Y=%b", A, B, y);

        A = 8'd170; B = 8'd0; car_in = 0; opcode = 4'd7; #10;
        $display("NOT     : A=%b Y=%b", A, y);

        A = 8'b10011001; B = 8'd0; car_in = 0; opcode = 4'd8; #10;
        $display("ROL     : A=%b Y=%b", A, y);

        A = 8'b10011001; B = 8'd0; car_in = 0; opcode = 4'd9; #10;
        $display("ROR     : A=%b Y=%b", A, y);

        A = 8'd0; B = 8'd0; car_in = 0; opcode = 4'd15; #10;
        $display("INVALID : Opcode=%d Invalid_op=%b", opcode, invalid_op);

        $finish;
    end
endmodule

alu_tb.vcd
$date
	Tue Sep 02 23:05:01 2025
$end
$version
	Icarus Verilog
$end
$timescale
	1s
$end
$scope module alu_tb $end
$var wire 1 ! zero $end
$var wire 8 " y [7:0] $end
$var wire 1 # parity $end
$var wire 1 $ invalid_op $end
$var wire 1 % borrow $end
$var wire 1 & Car_out $end
$var reg 8 ' A [7:0] $end
$var reg 8 ( B [7:0] $end
$var reg 1 ) car_in $end
$var reg 4 * opcode [3:0] $end
$scope module uut $end
$var wire 8 + A [7:0] $end
$var wire 8 , B [7:0] $end
$var wire 1 ) car_in $end
$var wire 4 - opcode [3:0] $end
$var wire 1 ! zero $end
$var wire 1 # parity $end
$var parameter 32 . bus_width $end
$var parameter 4 / op_add $end
$var parameter 4 0 op_add_with_carry $end
$var parameter 4 1 op_and $end
$var parameter 4 2 op_dec $end
$var parameter 4 3 op_inc $end
$var parameter 4 4 op_not $end
$var parameter 4 5 op_rol $end
$var parameter 4 6 op_ror $end
$var parameter 4 7 op_sub $end
$var reg 1 & Car_out $end
$var reg 1 % borrow $end
$var reg 1 $ invalid_op $end
$var reg 8 8 y [7:0] $end
$upscope $end
$upscope $end
$enddefinitions $end
$comment Show the parameter values. $end
$dumpall
b11 7
b1001 6
b1000 5
b111 4
b100 3
b101 2
b110 1
b10 0
b1 /
b1000 .
$end
#0
$dumpvars
b1111 8
b1 -
b101 ,
b1010 +
b1 *
0)
b101 (
b1010 '
0&
0%
0$
0#
b1111 "
0!
$end
#10
1&
0!
b101101 "
b101101 8
b10 *
b10 -
1)
b1100100 (
b1100100 ,
b11001000 '
b11001000 +
#20
1%
1#
0&
0!
b11111011 "
b11111011 8
b11 *
b11 -
0)
b1010 (
b1010 ,
b101 '
b101 +
#30
1&
0%
1!
0#
b0 "
b0 8
b100 *
b100 -
b0 (
b0 ,
b11111111 '
b11111111 +
#40
1%
0!
b11111111 "
b11111111 8
0&
b101 *
b101 -
b0 '
b0 +
#50
0%
1!
b0 "
b0 8
b110 *
b110 -
b1010101 (
b1010101 ,
b10101010 '
b10101010 +
#60
0!
b1010101 "
b1010101 8
b111 *
b111 -
b0 (
b0 ,
#70
0!
b110011 "
b110011 8
b1000 *
b1000 -
b10011001 '
b10011001 +
#80
0!
b11001100 "
b11001100 8
b1001 *
b1001 -
#90
1$
1!
b0 "
b0 8
b1111 *
b1111 -
b0 '
b0 +
